carconnectivity_connector_seatcupra-0.6.dist-info/licenses/LICENSE
carconnectivity_connectors/seatcupra/__init__.py
carconnectivity_connectors/seatcupra/_version.py
carconnectivity_connectors/seatcupra/capability.py
carconnectivity_connectors/seatcupra/charging.py
carconnectivity_connectors/seatcupra/climatization.py
carconnectivity_connectors/seatcupra/command_impl.py
carconnectivity_connectors/seatcupra/connector.py
carconnectivity_connectors/seatcupra/vehicle.py
carconnectivity_connectors/seatcupra/auth/__init__.py
carconnectivity_connectors/seatcupra/auth/auth_util.py
carconnectivity_connectors/seatcupra/auth/my_cupra_session.py
carconnectivity_connectors/seatcupra/auth/openid_session.py
carconnectivity_connectors/seatcupra/auth/session_manager.py
carconnectivity_connectors/seatcupra/auth/vw_web_session.py
carconnectivity_connectors/seatcupra/auth/helpers/blacklist_retry.py
carconnectivity_connectors/seatcupra/services/seatcupra_location_service.py
carconnectivity_connectors/seatcupra/ui/connector_ui.py
carconnectivity_connector_seatcupra-0.6.dist-info/METADATA
carconnectivity_connector_seatcupra-0.6.dist-info/WHEEL
carconnectivity_connector_seatcupra-0.6.dist-info/top_level.txt
carconnectivity_connector_seatcupra-0.6.dist-info/RECORD
